Search_Youtube_Caption/__init__.py
Search_Youtube_Caption/main.py
Search_Youtube_Caption/setting.py
Search_Youtube_Caption/utils.py
Search_Youtube_Caption/model/__init__.py
Search_Youtube_Caption/model/found.py
Search_Youtube_Caption/model/yt.py
Search_Youtube_Caption/pipeline/__init__.py
Search_Youtube_Caption/pipeline/pipeline.py
Search_Youtube_Caption/pipeline/Steps/__init__.py
Search_Youtube_Caption/pipeline/Steps/download_captions.py
Search_Youtube_Caption/pipeline/Steps/download_video.py
Search_Youtube_Caption/pipeline/Steps/edit_video.py
Search_Youtube_Caption/pipeline/Steps/initialize_yt.py
Search_Youtube_Caption/pipeline/Steps/postflight.py
Search_Youtube_Caption/pipeline/Steps/preflight.py
Search_Youtube_Caption/pipeline/Steps/read_caption.py
Search_Youtube_Caption/pipeline/Steps/search.py
Search_Youtube_Caption/pipeline/Steps/step.py
Search_Youtube_Caption/pipeline/Steps/video_list.py
Search_YouTube_Caption_Project-0.1.4.dist-info/LICENSE
Search_YouTube_Caption_Project-0.1.4.dist-info/METADATA
Search_YouTube_Caption_Project-0.1.4.dist-info/WHEEL
Search_YouTube_Caption_Project-0.1.4.dist-info/top_level.txt
Search_YouTube_Caption_Project-0.1.4.dist-info/RECORD
