Metadata-Version: 2.1
Name: Search-YouTube-Caption-Project
Version: 0.1.4
Summary: Produce a concatenated video of clips that mention the word from the youtube video
Home-page: https://github.com/me/myproject
Author: Winston Chang
Author-email: winston95213@gmail.com
License: MIT
Classifier: License :: OSI Approved :: MIT License
Classifier: Programming Language :: Python
Classifier: Programming Language :: Python :: 3
Classifier: Programming Language :: Python :: 3.6
Classifier: Programming Language :: Python :: Implementation :: CPython
Classifier: Programming Language :: Python :: Implementation :: PyPy
Requires-Python: >=3.9.0
License-File: LICENSE
Requires-Dist: moviepy
Requires-Dist: pytube
Requires-Dist: requests
Requires-Dist: urllib3
Requires-Dist: python-dotenv
